{
    "fluentMethods": true,
    "relationships": [
        {
            "relationshipType": "many-to-one",
            "relationshipName": "owner",
            "otherEntityName": "customer",
            "otherEntityField": "id"
        },
        {
            "relationshipType": "many-to-one",
            "relationshipName": "bank",
            "otherEntityName": "bank",
            "otherEntityField": "id"
        }
    ],
    "fields": [
        {
            "fieldName": "pin",
            "fieldType": "Long",
            "fieldValidateRules": [
                "required"
            ]
        },
        {
            "fieldName": "cardNumber",
            "fieldType": "Long",
            "fieldValidateRules": [
                "required"
            ]
        },
        {
            "fieldName": "validityDate",
            "fieldType": "Instant",
            "fieldValidateRules": [
                "required"
            ]
        }
    ],
    "changelogDate": "20180924143019",
    "entityTableName": "debit",
    "dto": "no",
    "pagination": "no",
    "service": "no",
    "jpaMetamodelFiltering": false,
    "microserviceName": "customer"
}